<annotation>
	<folder>to_label</folder>
	<filename>Rennes19_100 BRASSE DAMES FINALE C_2049.jpg</filename>
	<path>C:/Users/tchar/Documents/GitHub/swimmers_detection/swimmers_tracking/extractions/labelled_images/train/Rennes19_100 BRASSE DAMES FINALE C_2049.jpg</path>
	<source>
		<database>Unknown</database>
	</source>
	<size>
		<width>1600</width>
		<height>900</height>
		<depth>3</depth>
	</size>
	<segmented>0</segmented>
	<object>
		<name>swimmerwdd</name>
		<pose>Unspecified</pose>
		<truncated>0</truncated>
		<difficult>0</difficult>
		<bndbox>
			<xmin>355</xmin>
			<ymin>484</ymin>
			<xmax>497</xmax>
			<ymax>568</ymax>
		</bndbox>
	</object>
	<object>
		<name>swimmerwdd</name>
		<pose>Unspecified</pose>
		<truncated>0</truncated>
		<difficult>0</difficult>
		<bndbox>
			<xmin>482</xmin>
			<ymin>427</ymin>
			<xmax>617</xmax>
			<ymax>497</ymax>
		</bndbox>
	</object>
	<object>
		<name>swimmerwdd</name>
		<pose>Unspecified</pose>
		<truncated>0</truncated>
		<difficult>0</difficult>
		<bndbox>
			<xmin>682</xmin>
			<ymin>401</ymin>
			<xmax>801</xmax>
			<ymax>464</ymax>
		</bndbox>
	</object>
	<object>
		<name>swimmerwdd</name>
		<pose>Unspecified</pose>
		<truncated>0</truncated>
		<difficult>0</difficult>
		<bndbox>
			<xmin>750</xmin>
			<ymin>331</ymin>
			<xmax>849</xmax>
			<ymax>383</ymax>
		</bndbox>
	</object>
	<object>
		<name>swimmerwdd</name>
		<pose>Unspecified</pose>
		<truncated>0</truncated>
		<difficult>0</difficult>
		<bndbox>
			<xmin>854</xmin>
			<ymin>279</ymin>
			<xmax>943</xmax>
			<ymax>325</ymax>
		</bndbox>
	</object>
	<object>
		<name>swimmerwdd</name>
		<pose>Unspecified</pose>
		<truncated>0</truncated>
		<difficult>0</difficult>
		<bndbox>
			<xmin>1033</xmin>
			<ymin>257</ymin>
			<xmax>1149</xmax>
			<ymax>296</ymax>
		</bndbox>
	</object>
	<object>
		<name>swimmerwdd</name>
		<pose>Unspecified</pose>
		<truncated>0</truncated>
		<difficult>0</difficult>
		<bndbox>
			<xmin>1161</xmin>
			<ymin>200</ymin>
			<xmax>1245</xmax>
			<ymax>253</ymax>
		</bndbox>
	</object>
	<object>
		<name>swimmerwdd</name>
		<pose>Unspecified</pose>
		<truncated>0</truncated>
		<difficult>0</difficult>
		<bndbox>
			<xmin>1221</xmin>
			<ymin>140</ymin>
			<xmax>1302</xmax>
			<ymax>192</ymax>
		</bndbox>
	</object>
</annotation>
