<annotation>
	<folder>to_label</folder>
	<filename>Stanforf19_100 BRASSE MESSIEURS FA_832.jpg</filename>
	<path>C:/Users/tchar/Documents/GitHub/swimmers_detection/swimmers_tracking/extractions/labelled_images/train/Stanforf19_100 BRASSE MESSIEURS FA_832.jpg</path>
	<source>
		<database>Unknown</database>
	</source>
	<size>
		<width>1600</width>
		<height>900</height>
		<depth>3</depth>
	</size>
	<segmented>0</segmented>
	<object>
		<name>swimmerw</name>
		<pose>Unspecified</pose>
		<truncated>0</truncated>
		<difficult>0</difficult>
		<bndbox>
			<xmin>109</xmin>
			<ymin>295</ymin>
			<xmax>243</xmax>
			<ymax>471</ymax>
		</bndbox>
	</object>
	<object>
		<name>swimmerw</name>
		<pose>Unspecified</pose>
		<truncated>0</truncated>
		<difficult>0</difficult>
		<bndbox>
			<xmin>334</xmin>
			<ymin>267</ymin>
			<xmax>461</xmax>
			<ymax>413</ymax>
		</bndbox>
	</object>
	<object>
		<name>swimmerw</name>
		<pose>Unspecified</pose>
		<truncated>0</truncated>
		<difficult>0</difficult>
		<bndbox>
			<xmin>490</xmin>
			<ymin>209</ymin>
			<xmax>606</xmax>
			<ymax>375</ymax>
		</bndbox>
	</object>
	<object>
		<name>swimmerw</name>
		<pose>Unspecified</pose>
		<truncated>0</truncated>
		<difficult>0</difficult>
		<bndbox>
			<xmin>615</xmin>
			<ymin>229</ymin>
			<xmax>702</xmax>
			<ymax>331</ymax>
		</bndbox>
	</object>
	<object>
		<name>swimmerw</name>
		<pose>Unspecified</pose>
		<truncated>0</truncated>
		<difficult>0</difficult>
		<bndbox>
			<xmin>699</xmin>
			<ymin>192</ymin>
			<xmax>790</xmax>
			<ymax>309</ymax>
		</bndbox>
	</object>
	<object>
		<name>swimmerw</name>
		<pose>Unspecified</pose>
		<truncated>0</truncated>
		<difficult>0</difficult>
		<bndbox>
			<xmin>777</xmin>
			<ymin>192</ymin>
			<xmax>853</xmax>
			<ymax>293</ymax>
		</bndbox>
	</object>
	<object>
		<name>swimmerw</name>
		<pose>Unspecified</pose>
		<truncated>0</truncated>
		<difficult>0</difficult>
		<bndbox>
			<xmin>841</xmin>
			<ymin>175</ymin>
			<xmax>910</xmax>
			<ymax>261</ymax>
		</bndbox>
	</object>
	<object>
		<name>swimmerw</name>
		<pose>Unspecified</pose>
		<truncated>0</truncated>
		<difficult>0</difficult>
		<bndbox>
			<xmin>889</xmin>
			<ymin>173</ymin>
			<xmax>957</xmax>
			<ymax>261</ymax>
		</bndbox>
	</object>
</annotation>
