<annotation>
	<folder>to_label</folder>
	<filename>StRaphael18_100 NL MESSIEURS SERIE 8_149.jpg</filename>
	<path>C:/Users/tchar/Documents/GitHub/swimmers_detection/swimmers_tracking/extractions/labelled_images/train/StRaphael18_100 NL MESSIEURS SERIE 8_149.jpg</path>
	<source>
		<database>Unknown</database>
	</source>
	<size>
		<width>1600</width>
		<height>900</height>
		<depth>3</depth>
	</size>
	<segmented>0</segmented>
	<object>
		<name>swimmerw</name>
		<pose>Unspecified</pose>
		<truncated>0</truncated>
		<difficult>0</difficult>
		<bndbox>
			<xmin>855</xmin>
			<ymin>448</ymin>
			<xmax>913</xmax>
			<ymax>523</ymax>
		</bndbox>
	</object>
	<object>
		<name>swimmerw</name>
		<pose>Unspecified</pose>
		<truncated>0</truncated>
		<difficult>0</difficult>
		<bndbox>
			<xmin>219</xmin>
			<ymin>260</ymin>
			<xmax>326</xmax>
			<ymax>296</ymax>
		</bndbox>
	</object>
	<object>
		<name>swimmerw</name>
		<pose>Unspecified</pose>
		<truncated>0</truncated>
		<difficult>0</difficult>
		<bndbox>
			<xmin>337</xmin>
			<ymin>281</ymin>
			<xmax>438</xmax>
			<ymax>308</ymax>
		</bndbox>
	</object>
	<object>
		<name>swimmerw</name>
		<pose>Unspecified</pose>
		<truncated>0</truncated>
		<difficult>0</difficult>
		<bndbox>
			<xmin>482</xmin>
			<ymin>300</ymin>
			<xmax>539</xmax>
			<ymax>376</ymax>
		</bndbox>
	</object>
	<object>
		<name>swimmerw</name>
		<pose>Unspecified</pose>
		<truncated>0</truncated>
		<difficult>0</difficult>
		<bndbox>
			<xmin>625</xmin>
			<ymin>307</ymin>
			<xmax>713</xmax>
			<ymax>372</ymax>
		</bndbox>
	</object>
	<object>
		<name>swimmerw</name>
		<pose>Unspecified</pose>
		<truncated>0</truncated>
		<difficult>0</difficult>
		<bndbox>
			<xmin>782</xmin>
			<ymin>329</ymin>
			<xmax>861</xmax>
			<ymax>403</ymax>
		</bndbox>
	</object>
	<object>
		<name>swimmerw</name>
		<pose>Unspecified</pose>
		<truncated>0</truncated>
		<difficult>0</difficult>
		<bndbox>
			<xmin>957</xmin>
			<ymin>349</ymin>
			<xmax>1041</xmax>
			<ymax>420</ymax>
		</bndbox>
	</object>
	<object>
		<name>swimmerw</name>
		<pose>Unspecified</pose>
		<truncated>0</truncated>
		<difficult>0</difficult>
		<bndbox>
			<xmin>1139</xmin>
			<ymin>387</ymin>
			<xmax>1221</xmax>
			<ymax>445</ymax>
		</bndbox>
	</object>
	<object>
		<name>swimmerw</name>
		<pose>Unspecified</pose>
		<truncated>0</truncated>
		<difficult>0</difficult>
		<bndbox>
			<xmin>1337</xmin>
			<ymin>405</ymin>
			<xmax>1438</xmax>
			<ymax>464</ymax>
		</bndbox>
	</object>
</annotation>
